_espeak_ng
espeak_ng
