Metadata-Version: 2.1
Name: espeak-ng-python
Version: 1.0.5
Summary: Python wrapper for espeak-ng.
Home-page: https://github.com/justinokamoto/espeak-ng-python
Author: Justin Okamoto
License: GPLv3
Keywords: espeak pico festival tts text-to-speech
Classifier: Programming Language :: Python :: 3
Classifier: License :: OSI Approved :: GNU General Public License v3 or later (GPLv3+)
Classifier: Operating System :: MacOS
Classifier: Operating System :: POSIX :: Linux
Requires-Python: >=3.8
License-File: COPYING
